src/__init__.py
src/flakeranker/__init__.py
src/flakeranker/analyzer/__init__.py
src/flakeranker/analyzer/analyze.py
src/flakeranker/analyzer/utils.py
src/flakeranker/cli/__init__.py
src/flakeranker/cli/commands/__init__.py
src/flakeranker/cli/commands/analyze.py
src/flakeranker/cli/commands/label.py
src/flakeranker/cli/commands/rank.py
src/flakeranker/cli/commands/run.py
src/flakeranker/cli/main.py
src/flakeranker/cli/utils/__init__.py
src/flakeranker/cli/utils/ordered_group.py
src/flakeranker/core/__init__.py
src/flakeranker/core/config.py
src/flakeranker/labeler/__init__.py
src/flakeranker/labeler/label.py
src/flakeranker/labeler/patterns.csv
src/flakeranker/ranker/__init__.py
src/flakeranker/ranker/rank.py
src/flakeranker/ranker/utils.py
src/flakeranker/utils.py
src/preprocessing/__init__.py
src/preprocessing/log.py
src/scripts/patterns.csv
src/scripts/patterns_refined.csv
src/utils/__init__.py
src/utils/constants.py
src/utils/utils.py
src/utils/vizualization.py
flakeranker-0.0.6.dist-info/LICENSE
flakeranker-0.0.6.dist-info/METADATA
flakeranker-0.0.6.dist-info/WHEEL
flakeranker-0.0.6.dist-info/entry_points.txt
flakeranker-0.0.6.dist-info/RECORD
