Metadata-Version: 2.1
Name: flakeranker
Version: 0.0.6
Summary: Understanding and Prioritizing Flaky Job Failure Categories
Author: Henri Aïdasso
Author-email: ahenrij@gmail.com
Requires-Python: >=3.10,<4.0
Classifier: Programming Language :: Python :: 3
Classifier: Programming Language :: Python :: 3.10
Classifier: Programming Language :: Python :: 3.11
Classifier: Programming Language :: Python :: 3.12
Requires-Dist: clean-text[gpl] (>=0.6.0,<0.7.0)
Requires-Dist: click (>=8.1.8,<9.0.0)
Requires-Dist: pandas (>=2.2.2,<3.0.0)
Requires-Dist: pydantic (>=2.10.5,<3.0.0)
Requires-Dist: pydantic-settings (>=2.7.1,<3.0.0)
Requires-Dist: scikit-learn (>=1.5.0,<2.0.0)
Requires-Dist: tqdm (>=4.67.1,<5.0.0)
